list/main.py
listfiles1-1.0.0.dist-info/METADATA
listfiles1-1.0.0.dist-info/WHEEL
listfiles1-1.0.0.dist-info/top_level.txt
listfiles1-1.0.0.dist-info/RECORD
